typing_test_sdd/__init__.py
typing_test_sdd/main.py
typing_test_sdd/words.json
typing_test_sdd/Assets/logo.png
typing_test_sdd/Assets/main_image.png
typing_test_sdd/Assets/settingsbg.png
typing_test_sdd-1.1.0.dist-info/LICENSE
typing_test_sdd-1.1.0.dist-info/METADATA
typing_test_sdd-1.1.0.dist-info/WHEEL
typing_test_sdd-1.1.0.dist-info/entry_points.txt
typing_test_sdd-1.1.0.dist-info/top_level.txt
typing_test_sdd-1.1.0.dist-info/RECORD
