Metadata-Version: 2.1
Name: typing_test_sdd
Version: 1.1.0
Summary: TKinter GUI Typing Test - Gaurav Surve 122SDD2
Home-page: https://github.com/GauravS2507/Gaurav-Surve-SDD2-Project---Typing-Test
Author: Gaurav Surve
Platform: any
Classifier: Development Status :: 5 - Production/Stable
Classifier: Intended Audience :: End Users/Desktop
Classifier: Intended Audience :: Education
Classifier: Operating System :: OS Independent
Classifier: Programming Language :: Python
Classifier: Programming Language :: Python :: 3
Classifier: Topic :: Education
Classifier: Topic :: Games/Entertainment
License-File: LICENSE
Requires-Dist: customtkinter
Requires-Dist: pillow
